[
  {
    "name_en": "University of Alcalá",
    "city": ""
  },
  {
    "name_en": "University of Alicante",
    "city": ""
  },
  {
    "name_en": "University of Almería",
    "city": ""
  },
  {
    "name_en": "International University of Andalusia",
    "city": ""
  },
  {
    "name_en": "Catholic University of Ávila",
    "city": ""
  },
  {
    "name_en": "European University of the Atlantic",
    "city": ""
  },
  {
    "name_en": "University of the Middle Atlantic",
    "city": ""
  },
  {
    "name_en": "University of the Balearic Islands",
    "city": ""
  },
  {
    "name_en": "Autonomous University of Barcelona",
    "city": ""
  },
  {
    "name_en": "International University of Catalonia",
    "city": ""
  },
  {
    "name_en": "University of Barcelona",
    "city": ""
  },
  {
    "name_en": "University of the Basque Country",
    "city": ""
  },
  {
    "name_en": "University of Burgos",
    "city": ""
  },
  {
    "name_en": "University of Cádiz",
    "city": ""
  },
  {
    "name_en": "University of Cantabria",
    "city": ""
  },
  {
    "name_en": "Polytechnic University of Cartagena",
    "city": ""
  },
  {
    "name_en": "Polytechnic University of Catalonia",
    "city": ""
  },
  {
    "name_en": "University of Castilla–La Mancha",
    "city": ""
  },
  {
    "name_en": "Abat Oliba CEU University",
    "city": ""
  },
  {
    "name_en": "Universidad CEU Cardenal Herrera",
    "city": ""
  },
  {
    "name_en": "CEU San Pablo University",
    "city": ""
  },
  {
    "name_en": "Comillas Pontifical University",
    "city": ""
  },
  {
    "name_en": "University of A Coruña",
    "city": ""
  },
  {
    "name_en": "CUNEF University",
    "city": ""
  },
  {
    "name_en": "University of Deusto",
    "city": ""
  },
  {
    "name_en": "National University of Distance Education",
    "city": ""
  },
  {
    "name_en": "Miguel Hernández University of Elche",
    "city": ""
  },
  {
    "name_en": "ESIC University",
    "city": ""
  },
  {
    "name_en": "European University",
    "city": ""
  },
  {
    "name_en": "University of Extremadura",
    "city": ""
  },
  {
    "name_en": "Fernando Pessoa Canarias University",
    "city": ""
  },
  {
    "name_en": "University of Girona",
    "city": ""
  },
  {
    "name_en": "University of Granada",
    "city": ""
  },
  {
    "name_en": "University of Huelva",
    "city": ""
  },
  {
    "name_en": "IE University",
    "city": ""
  },
  {
    "name_en": "University of Jaén",
    "city": ""
  },
  {
    "name_en": "Jaume I University",
    "city": ""
  },
  {
    "name_en": "King Juan Carlos University",
    "city": ""
  },
  {
    "name_en": "University of La Laguna",
    "city": ""
  },
  {
    "name_en": "University of León",
    "city": ""
  },
  {
    "name_en": "University of Lleida",
    "city": ""
  },
  {
    "name_en": "Loyola University Andalusia",
    "city": ""
  },
  {
    "name_en": "Autonomous University of Madrid",
    "city": ""
  },
  {
    "name_en": "Complutense University of Madrid",
    "city": ""
  },
  {
    "name_en": "Universidad a Distancia de Madrid",
    "city": ""
  },
  {
    "name_en": "European University of Madrid",
    "city": ""
  },
  {
    "name_en": "Technical University of Madrid",
    "city": ""
  },
  {
    "name_en": "University of Málaga",
    "city": ""
  },
  {
    "name_en": "University of Murcia",
    "city": ""
  },
  {
    "name_en": "Menéndez Pelayo International University",
    "city": ""
  },
  {
    "name_en": "Miguel de Cervantes European University",
    "city": ""
  },
  {
    "name_en": "Mondragon University",
    "city": ""
  },
  {
    "name_en": "University of Navarre",
    "city": ""
  },
  {
    "name_en": "Public University of Navarre",
    "city": ""
  },
  {
    "name_en": "Nebrija University",
    "city": ""
  },
  {
    "name_en": "Open University of Catalonia",
    "city": ""
  },
  {
    "name_en": "University of Oviedo",
    "city": ""
  },
  {
    "name_en": "Pablo de Olavide University",
    "city": ""
  },
  {
    "name_en": "University of Las Palmas de Gran Canaria",
    "city": ""
  },
  {
    "name_en": "Pompeu Fabra University",
    "city": ""
  },
  {
    "name_en": "Harbour.Space University",
    "city": ""
  },
  {
    "name_en": "Ramon Llull University",
    "city": ""
  },
  {
    "name_en": "University of La Rioja",
    "city": ""
  },
  {
    "name_en": "International University of La Rioja",
    "city": ""
  },
  {
    "name_en": "Rovira i Virgili University",
    "city": ""
  },
  {
    "name_en": "University of Salamanca",
    "city": ""
  },
  {
    "name_en": "Pontifical University of Salamanca",
    "city": ""
  },
  {
    "name_en": "San Damaso Ecclesiastical University",
    "city": ""
  },
  {
    "name_en": "University of Santiago de Compostela",
    "city": ""
  },
  {
    "name_en": "University of Seville",
    "city": ""
  },
  {
    "name_en": "University of Valencia",
    "city": ""
  },
  {
    "name_en": "Valencian International University",
    "city": ""
  },
  {
    "name_en": "Polytechnic University of Valencia",
    "city": ""
  },
  {
    "name_en": "University of Valladolid",
    "city": ""
  },
  {
    "name_en": "University of Vic",
    "city": ""
  },
  {
    "name_en": "University of Vigo",
    "city": ""
  },
  {
    "name_en": "Villanueva University",
    "city": ""
  },
  {
    "name_en": "University of Zaragoza",
    "city": ""
  },
  {
    "name_en": "Alfonso X El Sabio University",
    "city": ""
  },
  {
    "name_en": "International University",
    "city": ""
  },
  {
    "name_en": "Catholic University",
    "city": ""
  },
  {
    "name_en": "Atlantic-Mediterranean Technological University",
    "city": ""
  },
  {
    "name_en": "Autonomous University",
    "city": ""
  },
  {
    "name_en": "Polytechnic University",
    "city": ""
  },
  {
    "name_en": "Charles III University",
    "city": ""
  },
  {
    "name_en": "National University",
    "city": ""
  },
  {
    "name_en": "Miguel Hernández University",
    "city": ""
  },
  {
    "name_en": "Complutense University",
    "city": ""
  },
  {
    "name_en": "Technical University",
    "city": ""
  },
  {
    "name_en": "Public University",
    "city": ""
  },
  {
    "name_en": "Open University",
    "city": ""
  },
  {
    "name_en": "Pontifical University",
    "city": ""
  },
  {
    "name_en": "Valencia Catholic University Saint Vincent Martyr",
    "city": ""
  }
]