[
  {
    "name_en": "University Canada West",
    "city": "access-date=2008-09-20"
  },
  {
    "name_en": "Alberta University",
    "city": ""
  },
  {
    "name_en": "Acadia University",
    "city": ""
  },
  {
    "name_en": "Algoma University",
    "city": ""
  },
  {
    "name_en": "Athabasca University",
    "city": ""
  },
  {
    "name_en": "Bishop's University",
    "city": ""
  },
  {
    "name_en": "Brandon University",
    "city": ""
  },
  {
    "name_en": "Brock University",
    "city": ""
  },
  {
    "name_en": "Cape Breton University",
    "city": ""
  },
  {
    "name_en": "Capilano University",
    "city": ""
  },
  {
    "name_en": "Carleton University",
    "city": ""
  },
  {
    "name_en": "Dalhousie University",
    "city": ""
  },
  {
    "name_en": "Emily Carr University",
    "city": ""
  },
  {
    "name_en": "Kwantlen Polytechnic University",
    "city": ""
  },
  {
    "name_en": "Lakehead University",
    "city": ""
  },
  {
    "name_en": "MacEwan University",
    "city": ""
  },
  {
    "name_en": "Mount Royal University",
    "city": ""
  },
  {
    "name_en": "Royal Roads University",
    "city": ""
  },
  {
    "name_en": "Simon Fraser University",
    "city": ""
  },
  {
    "name_en": "Thompson Rivers University",
    "city": ""
  },
  {
    "name_en": "Vancouver Island University",
    "city": ""
  },
  {
    "name_en": "Mount Allison University",
    "city": ""
  },
  {
    "name_en": "Memorial University",
    "city": ""
  },
  {
    "name_en": "Mount Saint Vincent University",
    "city": ""
  },
  {
    "name_en": "Nova Scotia College of Art and Design University",
    "city": ""
  },
  {
    "name_en": "Saint Francis Xavier University",
    "city": ""
  },
  {
    "name_en": "Laurentian University",
    "city": ""
  },
  {
    "name_en": "McMaster University",
    "city": ""
  },
  {
    "name_en": "Nipissing University",
    "city": ""
  },
  {
    "name_en": "Ontario College of Art and Design University",
    "city": ""
  },
  {
    "name_en": "Toronto Metropolitan University",
    "city": ""
  },
  {
    "name_en": "Trent University",
    "city": ""
  },
  {
    "name_en": "Ontario Tech University",
    "city": ""
  },
  {
    "name_en": "Wilfrid Laurier University",
    "city": ""
  },
  {
    "name_en": "York University",
    "city": ""
  },
  {
    "name_en": "McGill University",
    "city": ""
  },
  {
    "name_en": "Yukon University",
    "city": ""
  },
  {
    "name_en": "Northeastern University",
    "city": ""
  },
  {
    "name_en": "Niagara University",
    "city": ""
  },
  {
    "name_en": "Ambrose University",
    "city": ""
  },
  {
    "name_en": "Burman University",
    "city": ""
  },
  {
    "name_en": "Canadian Mennonite University",
    "city": ""
  },
  {
    "name_en": "Concordia University",
    "city": ""
  },
  {
    "name_en": "Crandall University",
    "city": ""
  },
  {
    "name_en": "Kingswood University",
    "city": ""
  },
  {
    "name_en": "Redeemer University",
    "city": ""
  },
  {
    "name_en": "St. Stephen's University",
    "city": ""
  },
  {
    "name_en": "Trinity Western University",
    "city": ""
  },
  {
    "name_en": "Tyndale University",
    "city": ""
  },
  {
    "name_en": "Yorkville University",
    "city": ""
  },
  {
    "name_en": "Alberta University of the Arts",
    "city": ""
  },
  {
    "name_en": "Emily Carr University of Art and Design",
    "city": ""
  },
  {
    "name_en": "Memorial University of Newfoundland",
    "city": ""
  },
  {
    "name_en": "Queen's University at Kingston",
    "city": ""
  },
  {
    "name_en": "Booth University College",
    "city": ""
  },
  {
    "name_en": "Concordia University of Edmonton",
    "city": ""
  },
  {
    "name_en": "Pacific Coast University for Workplace Health Sciences",
    "city": ""
  },
  {
    "name_en": "Providence University College and Theological Seminary",
    "city": ""
  },
  {
    "name_en": "St. Mary's University, Calgary",
    "city": ""
  }
]